jturtle/__init__.py
jturtle/turtle.py
jturtle-0.0.3.dist-info/LICENSE
jturtle-0.0.3.dist-info/METADATA
jturtle-0.0.3.dist-info/WHEEL
jturtle-0.0.3.dist-info/top_level.txt
jturtle-0.0.3.dist-info/RECORD
