Metadata-Version: 2.1
Name: jturtle
Version: 0.0.3
Summary: Simple Jupyter Turtle Library
Home-page: https://github.com/shwars/jturtle
Author: Dmitri Soshnikov
Author-email: dmitri@soshnikov.com
License: MIT license
Platform: UNKNOWN
Classifier: Programming Language :: Python :: 3
Classifier: Intended Audience :: Developers
Classifier: License :: OSI Approved :: MIT License
Classifier: Operating System :: OS Independent
Classifier: Topic :: Software Development
Classifier: Topic :: Software Development :: Libraries :: Python Modules
Requires-Dist: matplotlib
